MANIFEST.in
setup.py
bcrypt/__about__.py
bcrypt/__init__.py
cachecontrol/__init__.py
cachecontrol/_cmd.py
cachecontrol/adapter.py
cachecontrol/cache.py
cachecontrol/compat.py
cachecontrol/controller.py
cachecontrol/filewrapper.py
cachecontrol/heuristics.py
cachecontrol/serialize.py
cachecontrol/wrapper.py
cachecontrol/caches/__init__.py
cachecontrol/caches/file_cache.py
cachecontrol/caches/redis_cache.py
certifi/__init__.py
certifi/__main__.py
certifi/core.py
cffi/__init__.py
cffi/api.py
cffi/backend_ctypes.py
cffi/cffi_opcode.py
cffi/commontypes.py
cffi/cparser.py
cffi/error.py
cffi/ffiplatform.py
cffi/lock.py
cffi/model.py
cffi/pkgconfig.py
cffi/recompiler.py
cffi/setuptools_ext.py
cffi/vengine_cpy.py
cffi/vengine_gen.py
cffi/verifier.py
chardet/__init__.py
chardet/big5freq.py
chardet/big5prober.py
chardet/chardistribution.py
chardet/charsetgroupprober.py
chardet/charsetprober.py
chardet/codingstatemachine.py
chardet/compat.py
chardet/cp949prober.py
chardet/enums.py
chardet/escprober.py
chardet/escsm.py
chardet/eucjpprober.py
chardet/euckrfreq.py
chardet/euckrprober.py
chardet/euctwfreq.py
chardet/euctwprober.py
chardet/gb2312freq.py
chardet/gb2312prober.py
chardet/hebrewprober.py
chardet/jisfreq.py
chardet/jpcntx.py
chardet/langbulgarianmodel.py
chardet/langcyrillicmodel.py
chardet/langgreekmodel.py
chardet/langhebrewmodel.py
chardet/langhungarianmodel.py
chardet/langthaimodel.py
chardet/langturkishmodel.py
chardet/latin1prober.py
chardet/mbcharsetprober.py
chardet/mbcsgroupprober.py
chardet/mbcssm.py
chardet/sbcharsetprober.py
chardet/sbcsgroupprober.py
chardet/sjisprober.py
chardet/universaldetector.py
chardet/utf8prober.py
chardet/version.py
chardet/cli/__init__.py
chardet/cli/chardetect.py
click/__init__.py
click/_bashcomplete.py
click/_compat.py
click/_termui_impl.py
click/_textwrap.py
click/_unicodefun.py
click/_winconsole.py
click/core.py
click/decorators.py
click/exceptions.py
click/formatting.py
click/globals.py
click/parser.py
click/termui.py
netoprmgr.egg-info/PKG-INFO
netoprmgr.egg-info/SOURCES.txt
netoprmgr.egg-info/dependency_links.txt
netoprmgr.egg-info/requires.txt
netoprmgr.egg-info/top_level.txt
