Metadata-Version: 1.1
Name: netoprmgr
Version: 1.3.5
Summary: Project to Manage Network Operation.
Home-page: https://github.com/FunGuardian/netoprmgr
Author: Funguardian, Dedar, Luthfi
Author-email: cristiano.ramadhan@gmail.com
License: GPLv3+
Platform: UNKNOWN
Classifier: Development Status :: 3 - Alpha
Classifier: Intended Audience :: Developers
Classifier: License :: OSI Approved :: GNU General Public License v3 or later (GPLv3+)
Classifier: Programming Language :: Python :: 3.6
